LICENSE
README.md
setup.cfg
setup.py
bin/run_matlab
run_matlab/__init__.py
run_matlab/commands.py
run_matlab/install.sh
run_matlab/run.sh
run_matlab/version.py
run_matlab.egg-info/PKG-INFO
run_matlab.egg-info/SOURCES.txt
run_matlab.egg-info/dependency_links.txt
run_matlab.egg-info/requires.txt
run_matlab.egg-info/top_level.txt