Metadata-Version: 2.1
Name: run-matlab
Version: 1.0.0
Summary: Command Line MATLAB Function Caller with Automatic MATLAB Compiler Runtime (MCR) Installation
Home-page: https://github.com/hanjunlee21/run-time
Author: Hanjun Lee
Author-email: hanjun@mit.edu
License: MIT
Download-URL: https://github.com/hanjunlee21/run_matlab/archive/refs/tags/v.1.0.0.tar.gz
Keywords: matlab,matlab-compiler,matlab-runtime
Platform: UNKNOWN
Classifier: Development Status :: 3 - Alpha
Classifier: Intended Audience :: Science/Research
Classifier: Topic :: Scientific/Engineering :: Bio-Informatics
Classifier: License :: OSI Approved :: MIT License
Classifier: Programming Language :: Python :: 3
Classifier: Programming Language :: Python :: 3.0
Classifier: Programming Language :: Python :: 3.1
Classifier: Programming Language :: Python :: 3.2
Classifier: Programming Language :: Python :: 3.3
Classifier: Programming Language :: Python :: 3.4
Classifier: Programming Language :: Python :: 3.5
Classifier: Programming Language :: Python :: 3.6
Classifier: Programming Language :: Awk
Classifier: Programming Language :: Unix Shell
